laboneq/__init__.py
laboneq/_optional_deps.py
laboneq/_rust/__init__.pyi
laboneq/_rust/codegenerator/__init__.pyi
laboneq/_rust/compiler/__init__.pyi
laboneq/_rust.abi3.so
laboneq/_utils.py
laboneq/_version.py
laboneq/analysis/__init__.py
laboneq/analysis/_kernelutils.py
laboneq/analysis/fitting.py
laboneq/compiler/__init__.py
laboneq/compiler/common/__init__.py
laboneq/compiler/common/compiler_settings.py
laboneq/compiler/common/device_type.py
laboneq/compiler/common/feedback_connection.py
laboneq/compiler/common/iface_code_generator.py
laboneq/compiler/common/iface_compiler_output.py
laboneq/compiler/common/iface_linker.py
laboneq/compiler/common/integration_times.py
laboneq/compiler/common/play_wave_type.py
laboneq/compiler/common/pulse_parameters.py
laboneq/compiler/common/resource_usage.py
laboneq/compiler/common/result_shape.py
laboneq/compiler/common/signal_obj.py
laboneq/compiler/event_list/__init__.py
laboneq/compiler/event_list/event_list_generator.py
laboneq/compiler/event_list/event_type.py
laboneq/compiler/event_list/preorder_map.py
laboneq/compiler/experiment_access/__init__.py
laboneq/compiler/experiment_access/experiment_dao.py
laboneq/compiler/experiment_access/experiment_info_loader.py
laboneq/compiler/experiment_access/loader_base.py
laboneq/compiler/feedback_router/__init__.py
laboneq/compiler/feedback_router/feedback_router.py
laboneq/compiler/ir/__init__.py
laboneq/compiler/ir/acquire_group_ir.py
laboneq/compiler/ir/case_ir.py
laboneq/compiler/ir/interval_ir.py
laboneq/compiler/ir/ir.py
laboneq/compiler/ir/loop_ir.py
laboneq/compiler/ir/loop_iteration_ir.py
laboneq/compiler/ir/match_ir.py
laboneq/compiler/ir/oscillator_ir.py
laboneq/compiler/ir/phase_reset_ir.py
laboneq/compiler/ir/ppc_step_ir.py
laboneq/compiler/ir/pulse_ir.py
laboneq/compiler/ir/root_ir.py
laboneq/compiler/ir/section_ir.py
laboneq/compiler/ir/voltage_offset.py
laboneq/compiler/scheduler/__init__.py
laboneq/compiler/scheduler/parameter_store.py
laboneq-26.1.0.dist-info/METADATA
laboneq-26.1.0.dist-info/WHEEL
laboneq-26.1.0.dist-info/licenses/AUTHORS
laboneq-26.1.0.dist-info/licenses/LICENSE
laboneq-26.1.0.dist-info/RECORD
